{
"type": "FeatureCollection",
"crs": { "type": "name", "properties": { "name": "urn:ogc:def:crs:OGC:1.3:CRS84" } },
                                                                                
"features": [
{ "type": "Feature", "properties": { "ID_V": "273661v6", "TIMESTAMP": "2012-03-08T19:42:23Z", "UID": "155917", "USERNAME": "iccaldwell", "CHANGESET": "10912809" }, "geometry": { "type": "Point", "coordinates": [ -2.724336899999969, 52.057144600000072 ] } },
{ "type": "Feature", "properties": { "ID_V": "33328663v9", "TIMESTAMP": "2012-03-08T19:42:24Z", "UID": "155917", "USERNAME": "iccaldwell", "CHANGESET": "10912809" }, "geometry": { "type": "Point", "coordinates": [ -2.744515, 52.074164100000075 ] } },
{ "type": "Feature", "properties": { "ID_V": "392130281v2", "TIMESTAMP": "2012-03-08T19:42:26Z", "UID": "155917", "USERNAME": "iccaldwell", "CHANGESET": "10912809" }, "geometry": { "type": "Point", "coordinates": [ -2.744830899999954, 52.076209300000073 ] } },
{ "type": "Feature", "properties": { "ID_V": "387845191v4", "TIMESTAMP": "2012-03-08T19:42:24Z", "UID": "155917", "USERNAME": "iccaldwell", "CHANGESET": "10912809" }, "geometry": { "type": "Point", "coordinates": [ -2.744898699999965, 52.074398200000076 ] } },
{ "type": "Feature", "properties": { "ID_V": "25987381v2", "TIMESTAMP": "2012-03-08T19:42:22Z", "UID": "155917", "USERNAME": "iccaldwell", "CHANGESET": "10912809" }, "geometry": { "type": "Point", "coordinates": [ -2.716087699999946, 52.057929100000081 ] } },
{ "type": "Feature", "properties": { "ID_V": "391049724v2", "TIMESTAMP": "2012-03-08T19:42:24Z", "UID": "155917", "USERNAME": "iccaldwell", "CHANGESET": "10912809" }, "geometry": { "type": "Point", "coordinates": [ -2.744199499999979, 52.074163400000032 ] } },
{ "type": "Feature", "properties": { "ID_V": "395463307v2", "TIMESTAMP": "2012-03-08T19:42:27Z", "UID": "155917", "USERNAME": "iccaldwell", "CHANGESET": "10912809" }, "geometry": { "type": "Point", "coordinates": [ -2.744602599999951, 52.0743 ] } },
{ "type": "Feature", "properties": { "ID_V": "414245093v2", "TIMESTAMP": "2012-03-08T19:42:27Z", "UID": "155917", "USERNAME": "iccaldwell", "CHANGESET": "10912809" }, "geometry": { "type": "Point", "coordinates": [ -2.714611, 52.042514500000038 ] } },
{ "type": "Feature", "properties": { "ID_V": "1666303442v1", "TIMESTAMP": "2012-03-08T19:42:11Z", "UID": "155917", "USERNAME": "iccaldwell", "CHANGESET": "10912809" }, "geometry": { "type": "Point", "coordinates": [ -2.719295, 52.065354300000081 ] } },
{ "type": "Feature", "properties": { "ID_V": "1666303440v1", "TIMESTAMP": "2012-03-08T19:42:11Z", "UID": "155917", "USERNAME": "iccaldwell", "CHANGESET": "10912809" }, "geometry": { "type": "Point", "coordinates": [ -2.715017799999941, 52.058168100000046 ] } },
{ "type": "Feature", "properties": { "ID_V": "391515998v3", "TIMESTAMP": "2012-03-08T19:42:24Z", "UID": "155917", "USERNAME": "iccaldwell", "CHANGESET": "10912809" }, "geometry": { "type": "Point", "coordinates": [ -2.744876899999952, 52.076353 ] } },
{ "type": "Feature", "properties": { "ID_V": "1666303456v1", "TIMESTAMP": "2012-03-08T19:42:11Z", "UID": "155917", "USERNAME": "iccaldwell", "CHANGESET": "10912809" }, "geometry": { "type": "Point", "coordinates": [ -2.721437899999955, 52.065954300000044 ] } },
{ "type": "Feature", "properties": { "ID_V": "31819194v4", "TIMESTAMP": "2012-03-08T19:42:23Z", "UID": "155917", "USERNAME": "iccaldwell", "CHANGESET": "10912809" }, "geometry": { "type": "Point", "coordinates": [ -2.721682599999951, 52.065990800000066 ] } },
{ "type": "Feature", "properties": { "ID_V": "1666303461v1", "TIMESTAMP": "2012-03-08T19:42:12Z", "UID": "155917", "USERNAME": "iccaldwell", "CHANGESET": "10912809" }, "geometry": { "type": "Point", "coordinates": [ -2.745223399999929, 52.076519300000029 ] } },
{ "type": "Feature", "properties": { "ID_V": "1666303460v1", "TIMESTAMP": "2012-03-08T19:42:12Z", "UID": "155917", "USERNAME": "iccaldwell", "CHANGESET": "10912809" }, "geometry": { "type": "Point", "coordinates": [ -2.7450662, 52.076246200000071 ] } },
{ "type": "Feature", "properties": { "ID_V": "391516005v2", "TIMESTAMP": "2012-03-08T19:42:24Z", "UID": "155917", "USERNAME": "iccaldwell", "CHANGESET": "10912809" }, "geometry": { "type": "Point", "coordinates": [ -2.743916, 52.076319100000035 ] } },
{ "type": "Feature", "properties": { "ID_V": "391516003v2", "TIMESTAMP": "2012-03-08T19:42:24Z", "UID": "155917", "USERNAME": "iccaldwell", "CHANGESET": "10912809" }, "geometry": { "type": "Point", "coordinates": [ -2.743187, 52.07629460000004 ] } },
{ "type": "Feature", "properties": { "ID_V": "86862722v5", "TIMESTAMP": "2012-03-08T19:42:27Z", "UID": "155917", "USERNAME": "iccaldwell", "CHANGESET": "10912809" }, "geometry": { "type": "Point", "coordinates": [ -2.714515799999958, 52.042706900000042 ] } },
{ "type": "Feature", "properties": { "ID_V": "391516008v2", "TIMESTAMP": "2012-03-08T19:42:25Z", "UID": "155917", "USERNAME": "iccaldwell", "CHANGESET": "10912809" }, "geometry": { "type": "Point", "coordinates": [ -2.738624899999934, 52.076017600000057 ] } },
{ "type": "Feature", "properties": { "ID_V": "391516009v2", "TIMESTAMP": "2012-03-08T19:42:25Z", "UID": "155917", "USERNAME": "iccaldwell", "CHANGESET": "10912809" }, "geometry": { "type": "Point", "coordinates": [ -2.739769299999978, 52.076090700000066 ] } },
{ "type": "Feature", "properties": { "ID_V": "391516001v2", "TIMESTAMP": "2012-03-08T19:42:24Z", "UID": "155917", "USERNAME": "iccaldwell", "CHANGESET": "10912809" }, "geometry": { "type": "Point", "coordinates": [ -2.744465899999966, 52.076337300000034 ] } },
{ "type": "Feature", "properties": { "ID_V": "391516019v2", "TIMESTAMP": "2012-03-08T19:42:25Z", "UID": "155917", "USERNAME": "iccaldwell", "CHANGESET": "10912809" }, "geometry": { "type": "Point", "coordinates": [ -2.734153499999934, 52.07582240000005 ] } },
{ "type": "Feature", "properties": { "ID_V": "391516013v2", "TIMESTAMP": "2012-03-08T19:42:25Z", "UID": "155917", "USERNAME": "iccaldwell", "CHANGESET": "10912809" }, "geometry": { "type": "Point", "coordinates": [ -2.7408394, 52.076145500000052 ] } },
{ "type": "Feature", "properties": { "ID_V": "391516011v2", "TIMESTAMP": "2012-03-08T19:42:25Z", "UID": "155917", "USERNAME": "iccaldwell", "CHANGESET": "10912809" }, "geometry": { "type": "Point", "coordinates": [ -2.742152699999963, 52.076216900000077 ] } },
{ "type": "Feature", "properties": { "ID_V": "391516017v2", "TIMESTAMP": "2012-03-08T19:42:25Z", "UID": "155917", "USERNAME": "iccaldwell", "CHANGESET": "10912809" }, "geometry": { "type": "Point", "coordinates": [ -2.733327499999973, 52.075875100000076 ] } },
{ "type": "Feature", "properties": { "ID_V": "1666303437v1", "TIMESTAMP": "2012-03-08T19:42:11Z", "UID": "155917", "USERNAME": "iccaldwell", "CHANGESET": "10912809" }, "geometry": { "type": "Point", "coordinates": [ -2.724472499999934, 52.057156500000076 ] } },
{ "type": "Feature", "properties": { "ID_V": "392130273v2", "TIMESTAMP": "2012-03-08T19:42:26Z", "UID": "155917", "USERNAME": "iccaldwell", "CHANGESET": "10912809" }, "geometry": { "type": "Point", "coordinates": [ -2.744465, 52.07500170000003 ] } },
{ "type": "Feature", "properties": { "ID_V": "391516027v2", "TIMESTAMP": "2012-03-08T19:42:26Z", "UID": "155917", "USERNAME": "iccaldwell", "CHANGESET": "10912809" }, "geometry": { "type": "Point", "coordinates": [ -2.735488799999928, 52.07584410000004 ] } },
{ "type": "Feature", "properties": { "ID_V": "391516024v2", "TIMESTAMP": "2012-03-08T19:42:26Z", "UID": "155917", "USERNAME": "iccaldwell", "CHANGESET": "10912809" }, "geometry": { "type": "Point", "coordinates": [ -2.735786099999928, 52.075725300000045 ] } },
{ "type": "Feature", "properties": { "ID_V": "391516021v2", "TIMESTAMP": "2012-03-08T19:42:25Z", "UID": "155917", "USERNAME": "iccaldwell", "CHANGESET": "10912809" }, "geometry": { "type": "Point", "coordinates": [ -2.733678199999929, 52.07582240000005 ] } },
{ "type": "Feature", "properties": { "ID_V": "392130272v2", "TIMESTAMP": "2012-03-08T19:42:26Z", "UID": "155917", "USERNAME": "iccaldwell", "CHANGESET": "10912809" }, "geometry": { "type": "Point", "coordinates": [ -2.744655299999977, 52.074981800000046 ] } },
{ "type": "Feature", "properties": { "ID_V": "218654912v7", "TIMESTAMP": "2012-03-08T19:42:22Z", "UID": "155917", "USERNAME": "iccaldwell", "CHANGESET": "10912809" }, "geometry": { "type": "Point", "coordinates": [ -2.745269099999973, 52.076578700000027 ] } },
{ "type": "Feature", "properties": { "ID_V": "273648v2", "TIMESTAMP": "2012-03-08T19:42:22Z", "UID": "155917", "USERNAME": "iccaldwell", "CHANGESET": "10912809" }, "geometry": { "type": "Point", "coordinates": [ -2.744861, 52.075662700000066 ] } },
{ "type": "Feature", "properties": { "ID_V": "391516025v3", "TIMESTAMP": "2012-03-08T19:42:26Z", "UID": "155917", "USERNAME": "iccaldwell", "CHANGESET": "10912809" }, "geometry": { "type": "Point", "coordinates": [ -2.734497099999942, 52.075833900000077 ] } },
{ "type": "Feature", "properties": { "ID_V": "391516023v2", "TIMESTAMP": "2012-03-08T19:42:25Z", "UID": "155917", "USERNAME": "iccaldwell", "CHANGESET": "10912809" }, "geometry": { "type": "Point", "coordinates": [ -2.738074899999958, 52.076008500000057 ] } }
]
}
